dav_tools/__init__.py
dav_tools/_arg_parser.py
dav_tools/commands.py
dav_tools/database.py
dav_tools/devtools.py
dav_tools/files.py
dav_tools/messages/__init__.py
dav_tools/messages/__main__.py
dav_tools/messages/formatted_text.py
dav_tools/messages/text_format.py
dav_tools/messages/utils.py
dav_tools/requirements/__init__.py
dav_tools/requirements/__main__.py
dav_tools-0.4.22.dist-info/METADATA
dav_tools-0.4.22.dist-info/WHEEL
dav_tools-0.4.22.dist-info/licenses/LICENSE
dav_tools-0.4.22.dist-info/RECORD
